[{"Year":1997,"CountryCode":"GMB","CountryName":"Gambia","PartyName":"alliance for patriotic reorientation and construction","PartyAbbreviation":null,"PartyClassification":"Unknown","PartyCandidates":["Unknown"],"TotalAmountOfVotes":159938.0,"TotalVotePercentage":51.952211423522684,"TotalAmountOfSeatsGained":0},{"Year":1997,"CountryCode":"GMB","CountryName":"Gambia","PartyName":"united democratic party","PartyAbbreviation":null,"PartyClassification":"Unknown","PartyCandidates":["Unknown"],"TotalAmountOfVotes":105100.0,"TotalVotePercentage":34.139337872251964,"TotalAmountOfSeatsGained":0},{"Year":1997,"CountryCode":"GMB","CountryName":"Gambia","PartyName":"people's democratic organisation for independence and socialism","PartyAbbreviation":null,"PartyClassification":"Unknown","PartyCandidates":["Unknown"],"TotalAmountOfVotes":24272.0,"TotalVotePercentage":7.8842056026194065,"TotalAmountOfSeatsGained":0},{"Year":1997,"CountryCode":"GMB","CountryName":"Gambia","PartyName":"national reconciliation party","PartyAbbreviation":null,"PartyClassification":"Unknown","PartyCandidates":["Unknown"],"TotalAmountOfVotes":6639.0,"TotalVotePercentage":2.1565277272491032,"TotalAmountOfSeatsGained":0},{"Year":2007,"CountryCode":"GMB","CountryName":"Gambia","PartyName":"alliance for patriotic reorientation and construction","PartyAbbreviation":null,"PartyClassification":"Unknown","PartyCandidates":["kalifa jammeh","abdoulie same","alhagie sillah","aihagie b sheikh nyang","momodou sellou bah","momodou s touray","ebrima janko sanyang","Unknown","lamin kebba jammeh","foday jibani manka","momodou l ceesay","bafaye saidykhan","njai darboe","haddy jagne","mamma kandeh","kebba gaye","aba l yabou","bora b mass","kalipha kambi","abdou f h s jarjue","lamin m m bojang","adama charn","paul l mendy","abdoulie suku singhateh","yerro m c mballow","cherno m a cham","kabba touray","essa saidykhan","foday a jallow","lamin jadama","ebrima manneh","dawda manneh","ousman bah","alh e s l sallah","abdoulie kanagi jawla","ousainou sainey jaiteh","fabakary tombong jatta","sulayman joof","netty baldeh","muhammadu m jallow","cherno omar jallow","sainey mbye","bekai camara","phoday mahmod kebbeh"],"TotalAmountOfVotes":156573.0,"TotalVotePercentage":59.766618061334334,"TotalAmountOfSeatsGained":1},{"Year":2007,"CountryCode":"GMB","CountryName":"Gambia","PartyName":"united democratic party","PartyAbbreviation":null,"PartyClassification":"Unknown","PartyCandidates":["famara s bojang","ebrima a b pesseh njie","momodou a sarr","aziz pa boy fraser","mohamad saiba sanyang","alasan f k cessay","kebba l jammeh","kebba yira maimeh","pa jallow","kekoi k b baajo","kemenseng jammeh","junkungba dukureh","adama barrow","sait a joof","babading k k daffeh","karapha dampha","alhagie momodou l k sanneh","ousman g a kebbeh","lamin r darboe","ismaila sanneh","alasan bojang","kebba famara singhateh","lamin ceesay","alagie fatty","bunambass kongira","babuocarr k nyang","alfusainey jawara","amadou sanneh","ebrima k sonko"],"TotalAmountOfVotes":57368.0,"TotalVotePercentage":21.898356325436875,"TotalAmountOfSeatsGained":0},{"Year":2007,"CountryCode":"GMB","CountryName":"Gambia","PartyName":"national alliance for democracy and development","PartyAbbreviation":null,"PartyClassification":"Unknown","PartyCandidates":["fabakary b ceesay","foday sanyang","halifa sallah","suwaibou touray","sidia sana jatta"],"TotalAmountOfVotes":13990.0,"TotalVotePercentage":5.3402246024414639,"TotalAmountOfSeatsGained":0},{"Year":2007,"CountryCode":"GMB","CountryName":"Gambia","PartyName":"independent 4896","PartyAbbreviation":null,"PartyClassification":"Unknown","PartyCandidates":["ebrima jammeh"],"TotalAmountOfVotes":2080.0,"TotalVotePercentage":0.79397192087764434,"TotalAmountOfSeatsGained":1},{"Year":2007,"CountryCode":"GMB","CountryName":"Gambia","PartyName":"independent 4897","PartyAbbreviation":null,"PartyClassification":"Unknown","PartyCandidates":["ebrima a o samba"],"TotalAmountOfVotes":1841.0,"TotalVotePercentage":0.70274149343064574,"TotalAmountOfSeatsGained":0},{"Year":2007,"CountryCode":"GMB","CountryName":"Gambia","PartyName":"independent 4898","PartyAbbreviation":null,"PartyClassification":"Unknown","PartyCandidates":["ousman m m jallow"],"TotalAmountOfVotes":2089.0,"TotalVotePercentage":0.79740737630451874,"TotalAmountOfSeatsGained":0},{"Year":2007,"CountryCode":"GMB","CountryName":"Gambia","PartyName":"independent 4899","PartyAbbreviation":null,"PartyClassification":"Unknown","PartyCandidates":["mao darboe"],"TotalAmountOfVotes":389.0,"TotalVotePercentage":0.14848801789490559,"TotalAmountOfSeatsGained":0},{"Year":2007,"CountryCode":"GMB","CountryName":"Gambia","PartyName":"independent 4900","PartyAbbreviation":null,"PartyClassification":"Unknown","PartyCandidates":["abdou kolley"],"TotalAmountOfVotes":4952.0,"TotalVotePercentage":1.890263919320238,"TotalAmountOfSeatsGained":0},{"Year":2007,"CountryCode":"GMB","CountryName":"Gambia","PartyName":"national reconciliation party","PartyAbbreviation":null,"PartyClassification":"Unknown","PartyCandidates":["alhagie a s boye","babou kebbeh","omar s ceesay","samba jallow","samba baldeh","abdoulje jallow","fafanding saidy","hamat n k bah"],"TotalAmountOfVotes":14932.0,"TotalVotePercentage":5.6998022704543194,"TotalAmountOfSeatsGained":0},{"Year":2007,"CountryCode":"GMB","CountryName":"Gambia","PartyName":"independent 4901","PartyAbbreviation":null,"PartyClassification":"Unknown","PartyCandidates":["ebrima l s marenah"],"TotalAmountOfVotes":2401.0,"TotalVotePercentage":0.91650316443616553,"TotalAmountOfSeatsGained":0},{"Year":2007,"CountryCode":"GMB","CountryName":"Gambia","PartyName":"independent 4902","PartyAbbreviation":null,"PartyClassification":"Unknown","PartyCandidates":["alhagie s b siilah"],"TotalAmountOfVotes":2053.0,"TotalVotePercentage":0.78366555459702114,"TotalAmountOfSeatsGained":0},{"Year":2007,"CountryCode":"GMB","CountryName":"Gambia","PartyName":"independent 4903","PartyAbbreviation":null,"PartyClassification":"Unknown","PartyCandidates":["alhagie s m secka"],"TotalAmountOfVotes":2308.0,"TotalVotePercentage":0.88100345835846294,"TotalAmountOfSeatsGained":0},{"Year":2007,"CountryCode":"GMB","CountryName":"Gambia","PartyName":"independent 4904","PartyAbbreviation":null,"PartyClassification":"Unknown","PartyCandidates":["pa sainey jallow"],"TotalAmountOfVotes":998.0,"TotalVotePercentage":0.38095383511340825,"TotalAmountOfSeatsGained":0},{"Year":2012,"CountryCode":"GMB","CountryName":"Gambia","PartyName":"Alliance for Patriotic Reorientation and Construction","PartyAbbreviation":null,"PartyClassification":"Unknown","PartyCandidates":["Kalifa Jammeh","Abdoulie Saine","Alhagi Sillah","Babucarr Sheik Nyang","Momodou Sellu Bah","Samba Cham","Ebrima Jammeh","Matarr Kujabi","Bintanding Jarju","Borrie L.S.B. Kolley","Buba A. Bojang","Lamin Kebba Jammeh","Foday Jibani Manka","Lamin Hydara","Bafaye Saidykhan","Njai Darboe","Haddy Nyang-Jagne","Habiboulie K. Jawo","Amadou Khan","Saikou Susso","Bubacarr S. Fadera","Bora B. Mass","Yaya Dibba","Abdou F.H.S. Jarju","Alhasana Bojang","Pa Lamin Jatta","Abdou Colley","Alh. Ablie Suku Sighateh","Yerro M.C. Mballow","Sheriff Misba Hydara","Pa Malick Ceesaay","Kebba B. Nget","Foday A. Jallow","Lamin Jadama","Ebrima Manneh","Habsana Jallow","Ousman Bah","Ousman Njie","Abdoulie Kanaji Jawla","Ousainou Sainey Jaiteh","Fabakary Tombong Jatta","Sulayman Joof","Netty Baldeh","Ahmad Malick Njie","Omar Cherno Jallow","Sainey Mbye","Saidou V. Sabally","Alh. Kasum Jallow"],"TotalAmountOfVotes":80289.0,"TotalVotePercentage":49.490846329285581,"TotalAmountOfSeatsGained":1},{"Year":2012,"CountryCode":"GMB","CountryName":"Gambia","PartyName":"Independent 3954","PartyAbbreviation":null,"PartyClassification":"Unknown","PartyCandidates":["Dudu Kassa Jatta"],"TotalAmountOfVotes":2974.0,"TotalVotePercentage":1.8331997780928311,"TotalAmountOfSeatsGained":0},{"Year":2012,"CountryCode":"GMB","CountryName":"Gambia","PartyName":"Independent 3955","PartyAbbreviation":null,"PartyClassification":"Unknown","PartyCandidates":["Haddijatou Forbes"],"TotalAmountOfVotes":1797.0,"TotalVotePercentage":1.1076866177649016,"TotalAmountOfSeatsGained":0},{"Year":2012,"CountryCode":"GMB","CountryName":"Gambia","PartyName":"Independent 3956","PartyAbbreviation":null,"PartyClassification":"Unknown","PartyCandidates":["Alh. Mbye Baboucarr Manneh"],"TotalAmountOfVotes":1086.0,"TotalVotePercentage":0.669419959317019,"TotalAmountOfSeatsGained":0},{"Year":2012,"CountryCode":"GMB","CountryName":"Gambia","PartyName":"Independent 3957","PartyAbbreviation":null,"PartyClassification":"Unknown","PartyCandidates":["Muhammed Magassy"],"TotalAmountOfVotes":7045.0,"TotalVotePercentage":4.3426000123281758,"TotalAmountOfSeatsGained":1},{"Year":2012,"CountryCode":"GMB","CountryName":"Gambia","PartyName":"Independent 3958","PartyAbbreviation":null,"PartyClassification":"Unknown","PartyCandidates":["Ousman M. Nyassi"],"TotalAmountOfVotes":964.0,"TotalVotePercentage":0.59421808543426,"TotalAmountOfSeatsGained":0},{"Year":2012,"CountryCode":"GMB","CountryName":"Gambia","PartyName":"Independent 3959","PartyAbbreviation":null,"PartyClassification":"Unknown","PartyCandidates":["Abdou Sanneh"],"TotalAmountOfVotes":869.0,"TotalVotePercentage":0.53565924921407881,"TotalAmountOfSeatsGained":0},{"Year":2012,"CountryCode":"GMB","CountryName":"Gambia","PartyName":"Independent 3960","PartyAbbreviation":null,"PartyClassification":"Unknown","PartyCandidates":["Kebba Yorro Manneh"],"TotalAmountOfVotes":477.0,"TotalVotePercentage":0.2940269987055415,"TotalAmountOfSeatsGained":0},{"Year":2012,"CountryCode":"GMB","CountryName":"Gambia","PartyName":"Independent 3961","PartyAbbreviation":null,"PartyClassification":"Unknown","PartyCandidates":["Sainey Touray"],"TotalAmountOfVotes":2057.0,"TotalVotePercentage":1.2679529063675028,"TotalAmountOfSeatsGained":0},{"Year":2012,"CountryCode":"GMB","CountryName":"Gambia","PartyName":"Independent 3962","PartyAbbreviation":null,"PartyClassification":"Unknown","PartyCandidates":["Alkali Sillah"],"TotalAmountOfVotes":3710.0,"TotalVotePercentage":2.2868766565986562,"TotalAmountOfSeatsGained":0},{"Year":2012,"CountryCode":"GMB","CountryName":"Gambia","PartyName":"Independent 3963","PartyAbbreviation":null,"PartyClassification":"Unknown","PartyCandidates":["Modou Ibrahima Cham"],"TotalAmountOfVotes":4747.0,"TotalVotePercentage":2.9260925846021077,"TotalAmountOfSeatsGained":0},{"Year":2012,"CountryCode":"GMB","CountryName":"Gambia","PartyName":"Independent 3964","PartyAbbreviation":null,"PartyClassification":"Unknown","PartyCandidates":["Babanding K.K. Daffeh"],"TotalAmountOfVotes":1313.0,"TotalVotePercentage":0.80934475744313639,"TotalAmountOfSeatsGained":0},{"Year":2012,"CountryCode":"GMB","CountryName":"Gambia","PartyName":"Independent 3965","PartyAbbreviation":null,"PartyClassification":"Unknown","PartyCandidates":["Buba Ayi Sanneh"],"TotalAmountOfVotes":13903.0,"TotalVotePercentage":8.569931578622942,"TotalAmountOfSeatsGained":1},{"Year":2012,"CountryCode":"GMB","CountryName":"Gambia","PartyName":"Independent 3966","PartyAbbreviation":null,"PartyClassification":"Unknown","PartyCandidates":["Kebba Famara Singhateh"],"TotalAmountOfVotes":2855.0,"TotalVotePercentage":1.7598471306170254,"TotalAmountOfSeatsGained":0},{"Year":2012,"CountryCode":"GMB","CountryName":"Gambia","PartyName":"Independent 3967","PartyAbbreviation":null,"PartyClassification":"Unknown","PartyCandidates":["Muhammadou Tambura"],"TotalAmountOfVotes":2111.0,"TotalVotePercentage":1.3012389816926586,"TotalAmountOfSeatsGained":0},{"Year":2012,"CountryCode":"GMB","CountryName":"Gambia","PartyName":"Independent 3968","PartyAbbreviation":null,"PartyClassification":"Unknown","PartyCandidates":["Omar Tobb"],"TotalAmountOfVotes":4572.0,"TotalVotePercentage":2.8182210441965108,"TotalAmountOfSeatsGained":1},{"Year":2012,"CountryCode":"GMB","CountryName":"Gambia","PartyName":"National Reconciliation Party","PartyAbbreviation":null,"PartyClassification":"Unknown","PartyCandidates":["Alhagie A.S. Boye","Musa Sonko","Serign Bandeh Jadama","Samba Jallow","Samba Baldeh","Lamin Cham","Ousman Touray","Hamat NK Bah"],"TotalAmountOfVotes":14606.0,"TotalVotePercentage":9.0032669666522835,"TotalAmountOfSeatsGained":0},{"Year":2012,"CountryCode":"GMB","CountryName":"Gambia","PartyName":"Independent 3969","PartyAbbreviation":null,"PartyClassification":"Unknown","PartyCandidates":["Demba B.T. Sambou"],"TotalAmountOfVotes":3750.0,"TotalVotePercentage":2.3115330086913644,"TotalAmountOfSeatsGained":1},{"Year":2012,"CountryCode":"GMB","CountryName":"Gambia","PartyName":"Independent 3970","PartyAbbreviation":null,"PartyClassification":"Unknown","PartyCandidates":["Sheikh Omar Saho"],"TotalAmountOfVotes":5097.0,"TotalVotePercentage":3.1418356654133022,"TotalAmountOfSeatsGained":0},{"Year":2012,"CountryCode":"GMB","CountryName":"Gambia","PartyName":"Independent 3971","PartyAbbreviation":null,"PartyClassification":"Unknown","PartyCandidates":["Mamat S. Mbye"],"TotalAmountOfVotes":728.0,"TotalVotePercentage":0.44874560808728353,"TotalAmountOfSeatsGained":0}]