[{"CountryCode":"BGR","Type":"Parliamentary","Year":2017,"VoterTurnout":53.85,"TotalVotes":3682493,"Registration":6838235,"VapTurnout":62.79,"VotingAge":5864631,"Population":7101510,"InvalidVotes":7.97},{"CountryCode":"BGR","Type":"Parliamentary","Year":2014,"VoterTurnout":51.05,"TotalVotes":3501269,"Registration":6858304,"VapTurnout":60.88,"VotingAge":5750976,"Population":6924716,"InvalidVotes":6.2},{"CountryCode":"BGR","Type":"Parliamentary","Year":2013,"VoterTurnout":52.49,"TotalVotes":3632174,"Registration":6919260,"VapTurnout":59.69,"VotingAge":6084873,"Population":7282041,"InvalidVotes":2.48},{"CountryCode":"BGR","Type":"Parliamentary","Year":2009,"VoterTurnout":60.64,"TotalVotes":4323581,"Registration":7129965,"VapTurnout":72.43,"VotingAge":5969019,"Population":7204687,"InvalidVotes":2.25},{"CountryCode":"BGR","Type":"Parliamentary","Year":2005,"VoterTurnout":55.76,"TotalVotes":3747808,"Registration":6720941,"VapTurnout":62.41,"VotingAge":6004949,"Population":7450349,"InvalidVotes":2.7},{"CountryCode":"BGR","Type":"Parliamentary","Year":2001,"VoterTurnout":66.63,"TotalVotes":4608289,"Registration":6916151,"VapTurnout":72.1,"VotingAge":6391816,"Population":7932984,"InvalidVotes":0.9},{"CountryCode":"BGR","Type":"Parliamentary","Year":1997,"VoterTurnout":58.87,"TotalVotes":4291258,"Registration":7289956,"VapTurnout":66.9,"VotingAge":6414519,"Population":8330544,"InvalidVotes":0.8},{"CountryCode":"BGR","Type":"Parliamentary","Year":1994,"VoterTurnout":75.23,"TotalVotes":5264614,"Registration":6997954,"VapTurnout":80.98,"VotingAge":6501110,"Population":8443000,"InvalidVotes":1.2},{"CountryCode":"BGR","Type":"Parliamentary","Year":1991,"VoterTurnout":83.87,"TotalVotes":5694842,"Registration":6790006,"VapTurnout":84.54,"VotingAge":6736500,"Population":8982000,"InvalidVotes":2.7},{"CountryCode":"BGR","Type":"Presidential","Year":2016,"VoterTurnout":56.28,"TotalVotes":3947629,"Registration":7014723,"VapTurnout":66.87,"VotingAge":5903575,"Population":7144653,"InvalidVotes":3.04},{"CountryCode":"BGR","Type":"Presidential","Year":2011,"VoterTurnout":48.25,"TotalVotes":3334169,"Registration":6910491,"VapTurnout":56.14,"VotingAge":5939090,"Population":7093635,"InvalidVotes":3.14},{"CountryCode":"BGR","Type":"Presidential","Year":2006,"VoterTurnout":42.62,"TotalVotes":2757441,"Registration":6469224,"VapTurnout":46.14,"VotingAge":5975892,"Population":7385367,"InvalidVotes":2.1},{"CountryCode":"BGR","Type":"Presidential","Year":2001,"VoterTurnout":54.92,"TotalVotes":3784036,"Registration":6889638,"VapTurnout":61.78,"VotingAge":6125141,"Population":7932984,"InvalidVotes":0.2},{"CountryCode":"BGR","Type":"Presidential","Year":1996,"VoterTurnout":49.79,"TotalVotes":3358998,"Registration":6746056,"VapTurnout":52.16,"VotingAge":6440280,"Population":8364000,"InvalidVotes":0.6},{"CountryCode":"BGR","Type":"Presidential","Year":1992,"VoterTurnout":75.17,"TotalVotes":5154973,"Registration":6857942,"VapTurnout":80.48,"VotingAge":6405000,"Population":8540000,"InvalidVotes":-1.0},{"CountryCode":"BGR","Type":"EU Parliament","Year":2014,"VoterTurnout":36.1,"TotalVotes":2361966,"Registration":6543423,"VapTurnout":41.07,"VotingAge":5751084,"Population":6924716,"InvalidVotes":5.19},{"CountryCode":"BGR","Type":"EU Parliament","Year":2009,"VoterTurnout":38.92,"TotalVotes":2601677,"Registration":6684770,"VapTurnout":43.59,"VotingAge":5969019,"Population":7204687,"InvalidVotes":0.97},{"CountryCode":"BGR","Type":"EU Parliament","Year":2007,"VoterTurnout":29.22,"TotalVotes":1955466,"Registration":6691080,"VapTurnout":31.27,"VotingAge":6253762,"Population":7679290,"InvalidVotes":0.9}]